README.md
setup.py
douzero/__init__.py
douzero.egg-info/PKG-INFO
douzero.egg-info/SOURCES.txt
douzero.egg-info/dependency_links.txt
douzero.egg-info/requires.txt
douzero.egg-info/top_level.txt
douzero/dmc/__init__.py
douzero/dmc/arguments.py
douzero/dmc/dmc.py
douzero/dmc/env_utils.py
douzero/dmc/file_writer.py
douzero/dmc/models.py
douzero/dmc/utils.py
douzero/env/__init__.py
douzero/env/env.py
douzero/env/game.py
douzero/env/move_detector.py
douzero/env/move_generator.py
douzero/env/move_selector.py
douzero/env/utils.py
douzero/evaluation/__init__.py
douzero/evaluation/deep_agent.py
douzero/evaluation/random_agent.py
douzero/evaluation/rlcard_agent.py
douzero/evaluation/simulation.py