Metadata-Version: 2.1
Name: douzero
Version: 1.0.6
Summary: DouZero DouDizhu AI
Home-page: https://github.com/kwai/DouZero
Author: Daochen Zha
Author-email: daochen.zha@tamu.edu
License: Apache License 2.0
Keywords: DouDizhu,AI,Reinforcment Learning,RL,Torch,Poker
Platform: UNKNOWN
Classifier: Programming Language :: Python :: 3.9
Classifier: Programming Language :: Python :: 3.8
Classifier: Programming Language :: Python :: 3.7
Classifier: Programming Language :: Python :: 3.6
Classifier: License :: OSI Approved :: Apache Software License
Classifier: Operating System :: OS Independent
